aws_cidr_finder/__init__.py
aws_cidr_finder/__main__.py
aws_cidr_finder/boto_wrapper.py
aws_cidr_finder/core.py
aws_cidr_finder/custom_types.py
aws_cidr_finder/py.typed
aws_cidr_finder-0.6.3.dist-info/licenses/LICENSE
aws_cidr_finder-0.6.3.dist-info/METADATA
aws_cidr_finder-0.6.3.dist-info/WHEEL
aws_cidr_finder-0.6.3.dist-info/entry_points.txt
aws_cidr_finder-0.6.3.dist-info/top_level.txt
aws_cidr_finder-0.6.3.dist-info/RECORD
