Metadata-Version: 2.4
Name: aws-cidr-finder
Version: 0.6.3
Summary: A CLI tool and library for finding unused CIDR blocks in AWS VPCs.
Home-page: https://github.com/cooperwalbrun/aws-cidr-finder
Author: cooperwalbrun
Author-email: mail@cooperwalbrun.io
Platform: any
Classifier: Programming Language :: Python :: 3.10
Classifier: Programming Language :: Python :: 3.11
Classifier: Programming Language :: Python :: 3.12
Classifier: Programming Language :: Python :: 3.13
Classifier: License :: OSI Approved :: GNU General Public License v3 (GPLv3)
Classifier: Operating System :: OS Independent
Requires-Python: <4,>=3.10
License-File: LICENSE
Requires-Dist: boto3<2,>=1.21
Requires-Dist: boto3-stubs[essential]<2,>=1.21
Requires-Dist: importlib-metadata
Requires-Dist: tabulate<1,>=0.8.9
Requires-Dist: types-tabulate<1,>=0.8.9
Provides-Extra: testing
Requires-Dist: mypy; extra == "testing"
Requires-Dist: pytest; extra == "testing"
Requires-Dist: pytest-cov; extra == "testing"
Requires-Dist: pytest-mock; extra == "testing"
Requires-Dist: tox; extra == "testing"
Provides-Extra: github-actions
Requires-Dist: mypy; extra == "github-actions"
Requires-Dist: pytest; extra == "github-actions"
Requires-Dist: pytest-cov; extra == "github-actions"
Requires-Dist: pytest-mock; extra == "github-actions"
Requires-Dist: tox; extra == "github-actions"
Requires-Dist: tox-gh-actions; extra == "github-actions"
Provides-Extra: development
Requires-Dist: mypy; extra == "development"
Requires-Dist: pytest; extra == "development"
Requires-Dist: pytest-cov; extra == "development"
Requires-Dist: pytest-mock; extra == "development"
Requires-Dist: tox; extra == "development"
Requires-Dist: yapf; extra == "development"
Dynamic: license-file
